LICENSE
MANIFEST.in
README.md
setup.py
nonebot_plugin_hoshino_sign/STHUPO.TTF
nonebot_plugin_hoshino_sign/__init__.py
nonebot_plugin_hoshino_sign/base.py
nonebot_plugin_hoshino_sign/config.py
nonebot_plugin_hoshino_sign/utils.py
nonebot_plugin_hoshino_sign.egg-info/PKG-INFO
nonebot_plugin_hoshino_sign.egg-info/SOURCES.txt
nonebot_plugin_hoshino_sign.egg-info/dependency_links.txt
nonebot_plugin_hoshino_sign.egg-info/requires.txt
nonebot_plugin_hoshino_sign.egg-info/top_level.txt
nonebot_plugin_hoshino_sign/image/frame.png
nonebot_plugin_hoshino_sign/image/shadow.png
nonebot_plugin_hoshino_sign/image/sign_bg/1.png
nonebot_plugin_hoshino_sign/image/sign_bg/10.png
nonebot_plugin_hoshino_sign/image/sign_bg/11.png
nonebot_plugin_hoshino_sign/image/sign_bg/12.png
nonebot_plugin_hoshino_sign/image/sign_bg/13.png
nonebot_plugin_hoshino_sign/image/sign_bg/14.png
nonebot_plugin_hoshino_sign/image/sign_bg/15.png
nonebot_plugin_hoshino_sign/image/sign_bg/16.png
nonebot_plugin_hoshino_sign/image/sign_bg/17.png
nonebot_plugin_hoshino_sign/image/sign_bg/18.png
nonebot_plugin_hoshino_sign/image/sign_bg/19.png
nonebot_plugin_hoshino_sign/image/sign_bg/2.png
nonebot_plugin_hoshino_sign/image/sign_bg/20.png
nonebot_plugin_hoshino_sign/image/sign_bg/21.png
nonebot_plugin_hoshino_sign/image/sign_bg/22.png
nonebot_plugin_hoshino_sign/image/sign_bg/23.png
nonebot_plugin_hoshino_sign/image/sign_bg/24.png
nonebot_plugin_hoshino_sign/image/sign_bg/25.png
nonebot_plugin_hoshino_sign/image/sign_bg/26.png
nonebot_plugin_hoshino_sign/image/sign_bg/27.png
nonebot_plugin_hoshino_sign/image/sign_bg/28.png
nonebot_plugin_hoshino_sign/image/sign_bg/29.png
nonebot_plugin_hoshino_sign/image/sign_bg/3.png
nonebot_plugin_hoshino_sign/image/sign_bg/30.png
nonebot_plugin_hoshino_sign/image/sign_bg/31.png
nonebot_plugin_hoshino_sign/image/sign_bg/32.png
nonebot_plugin_hoshino_sign/image/sign_bg/33.png
nonebot_plugin_hoshino_sign/image/sign_bg/34.png
nonebot_plugin_hoshino_sign/image/sign_bg/35.png
nonebot_plugin_hoshino_sign/image/sign_bg/36.png
nonebot_plugin_hoshino_sign/image/sign_bg/37.png
nonebot_plugin_hoshino_sign/image/sign_bg/38.png
nonebot_plugin_hoshino_sign/image/sign_bg/39.png
nonebot_plugin_hoshino_sign/image/sign_bg/4.png
