Metadata-Version: 2.1
Name: nonebot-plugin-hoshino-sign
Version: 2.3.4
Summary: 一个从 hoshino 搬过来的 nonebot2 插件
Home-page: https://github.com/zhulinyv/nonebot_plugin_hoshino_sign
Author: (๑•小丫头片子•๑)
Author-email: zhulinyv2005@outlook.com
License: MIT
Classifier: License :: OSI Approved :: MIT License
Classifier: Programming Language :: Python
Classifier: Programming Language :: Python :: 3
Classifier: Programming Language :: Python :: 3.6
Classifier: Programming Language :: Python :: Implementation :: CPython
Classifier: Programming Language :: Python :: Implementation :: PyPy
Requires-Python: >=3.6.0
License-File: LICENSE
Requires-Dist: nonebot2
Requires-Dist: nonebot-adapter-onebot
Requires-Dist: nonebot_plugin_guild_patch
Requires-Dist: pil_utils
Requires-Dist: httpx
Requires-Dist: pytz
Requires-Dist: pillow
Requires-Dist: ujson
